konradtechnologies_rtms/__init__.py
konradtechnologies_rtms/enum_types.py
konradtechnologies_rtms/rtms_client.py
konradtechnologies_rtms/target.py
konradtechnologies_rtms/communication/__init__.py
konradtechnologies_rtms/communication/base_communication.py
konradtechnologies_rtms/communication/command_set.py
konradtechnologies_rtms/communication/scpi_communication.py
konradtechnologies_rtms_python-0.2.0.dist-info/LICENSE
konradtechnologies_rtms_python-0.2.0.dist-info/METADATA
konradtechnologies_rtms_python-0.2.0.dist-info/WHEEL
konradtechnologies_rtms_python-0.2.0.dist-info/top_level.txt
konradtechnologies_rtms_python-0.2.0.dist-info/RECORD
