Metadata-Version: 2.1
Name: konradtechnologies-rtms-python
Version: 0.2.0
Summary: A communication library for interfacing with the KT-RTMS software.
Home-page: https://github.com/konradtechnologies/rtms-python
Author: Konrad Technologies
Author-email: info@konrad-technologies.com
License: UNKNOWN
Platform: UNKNOWN
Classifier: Programming Language :: Python :: 3
Classifier: Programming Language :: Python :: 3.6
Classifier: Programming Language :: Python :: 3.7
Classifier: Programming Language :: Python :: 3.8
Classifier: Programming Language :: Python :: 3.9
Classifier: Programming Language :: Python :: 3.10
Classifier: License :: OSI Approved :: MIT License
Classifier: Operating System :: OS Independent
Requires-Python: >=3.6
License-File: LICENSE
Requires-Dist: packaging
Requires-Dist: numpy
